dharanitharan/__init__.py
dharanitharan/module1.py
dharanitharan/module2.py
dharanitharan-1.0.0.dist-info/METADATA
dharanitharan-1.0.0.dist-info/WHEEL
dharanitharan-1.0.0.dist-info/top_level.txt
dharanitharan-1.0.0.dist-info/RECORD
