Metadata-Version: 2.1
Name: dharanitharan
Version: 1.0.0
Summary: A brief description of your package
Author: sridharanitharan
Author-email: username420sri@gamil.com
Classifier: Programming Language :: Python :: 3
Classifier: License :: OSI Approved :: MIT License
Classifier: Operating System :: OS Independent
Requires-Python: >=3.6
